vphelpers/__init__.py
vphelpers/date.py
vphelpers/dict_.py
vphelpers/list_.py
vphelpers/path.py
vphelpers/py.typed
vphelpers/str_.py
vphelpers/types_.py
vphelpers-0.1.0.dist-info/METADATA
vphelpers-0.1.0.dist-info/WHEEL
vphelpers-0.1.0.dist-info/RECORD
