Metadata-Version: 2.1
Name: vphelpers
Version: 0.1.0
Summary: Often used functions in vladimirs-git projects
Home-page: https://github.com/vladimirs-git/vphelpers
License: MIT
Author: Vladimir Prusakov
Author-email: vladimir.prusakovs@gmail.com
Requires-Python: >=3.8,<4.0
Classifier: License :: OSI Approved :: MIT License
Classifier: Programming Language :: Python :: 3
Classifier: Programming Language :: Python :: 3.8
Classifier: Programming Language :: Python :: 3.9
Classifier: Programming Language :: Python :: 3.10
Classifier: Programming Language :: Python :: 3.11
Provides-Extra: test
Project-URL: Bug Tracker, https://github.com/vladimirs-git/vphelpers/issues
Project-URL: Download URL, https://github.com/vladimirs-git/vphelpers/archive/refs/tags/0.1.0.tar.gz
Project-URL: Repository, https://github.com/vladimirs-git/vphelpers
